dump_hls/__init__.py
dump_hls/cli.py
dump_hls/main.py
dump_hls/release.py
dump_hls-1.0.1.dist-info/LICENSE
dump_hls-1.0.1.dist-info/METADATA
dump_hls-1.0.1.dist-info/WHEEL
dump_hls-1.0.1.dist-info/entry_points.txt
dump_hls-1.0.1.dist-info/top_level.txt
dump_hls-1.0.1.dist-info/RECORD
