Metadata-Version: 2.1
Name: dump-hls
Version: 1.0.1
Summary: A python package to dump any HLS stream as it is
Home-page: https://github.com/milliele/DumpHls
Author: milliele
Author-email: milliele@qq.com
License: Apache Software License 2.0
Requires-Dist: click
Requires-Dist: aioresponses
Requires-Dist: joblib
Requires-Dist: asyncio
Requires-Dist: aiohttp
Requires-Dist: tqdm
Requires-Dist: requests
